micropm4py/__init__.py
micropm4py/conversion/__init__.py
micropm4py/conversion/dfg/__init__.py
micropm4py/conversion/dfg/dfg_mining.py
micropm4py/conversion/dfg/traces_to_dfg.py
micropm4py/conversion/pm4py/__init__.py
micropm4py/conversion/pm4py/dfg.py
micropm4py/conversion/pm4py/petri.py
micropm4py/conversion/pm4py/traces.py
micropm4py/discovery/__init__.py
micropm4py/discovery/alpha.py
micropm4py/log/__init__.py
micropm4py/log/csv_export_traces.py
micropm4py/log/csv_export_traces_file.py
micropm4py/log/csv_import_traces.py
micropm4py/log/csv_import_traces_file.py
micropm4py/log/dfg_import_export.py
micropm4py/log/postprocessing.py
micropm4py/log/xes_export_traces.py
micropm4py/log/xes_export_traces_file.py
micropm4py/log/xes_import_traces.py
micropm4py/log/xes_import_traces_file.py
micropm4py/log/xes_import_traces_file_minimal_dfg.py
micropm4py/log/xes_import_traces_file_minimal_it.py
micropm4py/log/xes_import_traces_file_standard.py
micropm4py/petrinet/__init__.py
micropm4py/petrinet/alignments.py
micropm4py/petrinet/petrinet_exec.py
micropm4py/petrinet/petrinet_export.py
micropm4py/petrinet/petrinet_export_file.py
micropm4py/petrinet/petrinet_import.py
micropm4py/petrinet/petrinet_import_file.py
micropm4py/random/__init__.py
micropm4py/random/expon.py
micropm4py/random/normal.py
micropm4py/util/__init__.py
micropm4py/util/copy.py
micropm4py/visualization/__init__.py
micropm4py/visualization/dfg_print.py
micropm4py/visualization/dfg_saver.py
micropm4py/visualization/petri_print.py
micropm4py/visualization/petri_saver.py
micropm4py-0.2.1.dist-info/LICENSE
micropm4py-0.2.1.dist-info/METADATA
micropm4py-0.2.1.dist-info/WHEEL
micropm4py-0.2.1.dist-info/top_level.txt
micropm4py-0.2.1.dist-info/RECORD
