Metadata-Version: 2.1
Name: micropm4py
Version: 0.2.1
Summary: MicroPM4Py - Process Mining for Micro-Controllers
Home-page: http://www.pm4py.org
Author: Alessandro Berti
Author-email: alessandro.berti89@gmail.com
License: GPL 3.0
Project-URL: Documentation, https://www.micropm4py.org/documentation.html
Project-URL: Source, https://github.com/Javert899/micropm4py/tree/master/micropm4py
Project-URL: Tracker, https://github.com/Javert899/micropm4py/issues
Platform: UNKNOWN
